invenio_cern_sync/__init__.py
invenio_cern_sync/config.py
invenio_cern_sync/errors.py
invenio_cern_sync/ext.py
invenio_cern_sync/logging.py
invenio_cern_sync/tasks.py
invenio_cern_sync/utils.py
invenio_cern_sync/authz/__init__.py
invenio_cern_sync/authz/client.py
invenio_cern_sync/authz/mapper.py
invenio_cern_sync/authz/serializer.py
invenio_cern_sync/groups/__init__.py
invenio_cern_sync/groups/sync.py
invenio_cern_sync/ldap/__init__.py
invenio_cern_sync/ldap/client.py
invenio_cern_sync/ldap/mapper.py
invenio_cern_sync/ldap/serializer.py
invenio_cern_sync/sso/__init__.py
invenio_cern_sync/sso/api.py
invenio_cern_sync/users/__init__.py
invenio_cern_sync/users/api.py
invenio_cern_sync/users/profile.py
invenio_cern_sync/users/sync.py
invenio_cern_sync-0.3.0.dist-info/licenses/LICENSE
invenio_cern_sync-0.3.0.dist-info/METADATA
invenio_cern_sync-0.3.0.dist-info/WHEEL
invenio_cern_sync-0.3.0.dist-info/entry_points.txt
invenio_cern_sync-0.3.0.dist-info/top_level.txt
invenio_cern_sync-0.3.0.dist-info/RECORD
