Metadata-Version: 2.4
Name: invenio-cern-sync
Version: 0.3.0
Summary: Integrates CERN databases and login with Invenio
Home-page: https://github.com/cerndocumentserver/invenio-cern-sync
Author: CERN
Author-email: info@inveniosoftware.org
License: MIT
Keywords: invenio-cern-sync
Platform: any
Classifier: Development Status :: 1 - Planning
Requires-Python: >=3.9
License-File: LICENSE
Requires-Dist: invenio-accounts<7.0.0,>=6.0.0
Requires-Dist: invenio-celery<3.0.0,>=2.0.0
Requires-Dist: invenio-oauthclient<6.0.0,>=5.0.0
Requires-Dist: invenio-userprofiles<5.0.0,>=4.0.0
Provides-Extra: tests
Requires-Dist: invenio-app>=2.0.0; extra == "tests"
Requires-Dist: invenio-db[mysql,postgresql]<3.0.0,>=2.0.0; extra == "tests"
Requires-Dist: pytest-invenio<4.0.0,>=3.0.0; extra == "tests"
Requires-Dist: pytest-black-ng>=0.4.0; extra == "tests"
Provides-Extra: opensearch2
Requires-Dist: invenio-search[opensearch2]<4.0.0,>=3.0.0; extra == "opensearch2"
Provides-Extra: ldap
Requires-Dist: python-ldap>=3.4.0; extra == "ldap"
Dynamic: license-file
